{"userid":175,"gp":[{"itemid":"629","rating":"3","timestamp":"877107942"},{"itemid":"496","rating":"5","timestamp":"877108098"},{"itemid":"193","rating":"4","timestamp":"877108098"},{"itemid":"419","rating":"5","timestamp":"877108098"},{"itemid":"508","rating":"1","timestamp":"877107712"},{"itemid":"172","rating":"5","timestamp":"877107339"},{"itemid":"11","rating":"5","timestamp":"877107339"},{"itemid":"273","rating":"2","timestamp":"877107640"},{"itemid":"869","rating":"3","timestamp":"877107500"},{"itemid":"56","rating":"2","timestamp":"877107790"},{"itemid":"176","rating":"3","timestamp":"877107255"},{"itemid":"669","rating":"1","timestamp":"877107790"},{"itemid":"483","rating":"5","timestamp":"877107339"},{"itemid":"660","rating":"3","timestamp":"877107836"},{"itemid":"132","rating":"3","timestamp":"877107712"},{"itemid":"100","rating":"2","timestamp":"877107712"},{"itemid":"147","rating":"3","timestamp":"877108146"},{"itemid":"133","rating":"4","timestamp":"877107390"},{"itemid":"88","rating":"4","timestamp":"877108146"},{"itemid":"187","rating":"4","timestamp":"877107338"},{"itemid":"127","rating":"5","timestamp":"877107640"},{"itemid":"9","rating":"4","timestamp":"877108146"},{"itemid":"215","rating":"5","timestamp":"877107500"},{"itemid":"12","rating":"4","timestamp":"877108146"},{"itemid":"195","rating":"3","timestamp":"877107790"},{"itemid":"50","rating":"5","timestamp":"877107138"},{"itemid":"136","rating":"4","timestamp":"877108051"},{"itemid":"566","rating":"3","timestamp":"877108015"},{"itemid":"96","rating":"3","timestamp":"877108051"},{"itemid":"183","rating":"4","timestamp":"877107942"},{"itemid":"234","rating":"5","timestamp":"877108015"},{"itemid":"111","rating":"4","timestamp":"877108015"},{"itemid":"71","rating":"4","timestamp":"877107942"},{"itemid":"31","rating":"4","timestamp":"877108051"},{"itemid":"64","rating":"5","timestamp":"877107552"},{"itemid":"661","rating":"4","timestamp":"877107432"},{"itemid":"186","rating":"4","timestamp":"877107790"},{"itemid":"98","rating":"5","timestamp":"877107390"}]}
{"userid":387,"gp":[{"itemid":"56","rating":"5","timestamp":"886479649"},{"itemid":"180","rating":"4","timestamp":"886479737"},{"itemid":"1007","rating":"5","timestamp":"886480623"},{"itemid":"461","rating":"5","timestamp":"886483753"},{"itemid":"393","rating":"2","timestamp":"886483009"},{"itemid":"1008","rating":"4","timestamp":"886481183"},{"itemid":"1538","rating":"3","timestamp":"886481151"},{"itemid":"1014","rating":"3","timestamp":"886480789"},{"itemid":"116","rating":"3","timestamp":"886480206"},{"itemid":"48","rating":"4","timestamp":"886483753"},{"itemid":"83","rating":"4","timestamp":"886480244"},{"itemid":"39","rating":"3","timestamp":"886483049"},{"itemid":"24","rating":"5","timestamp":"886484522"},{"itemid":"603","rating":"4","timestamp":"886480548"},{"itemid":"64","rating":"3","timestamp":"886480206"},{"itemid":"50","rating":"5","timestamp":"886480108"},{"itemid":"61","rating":"3","timestamp":"886483565"},{"itemid":"547","rating":"4","timestamp":"886484561"},{"itemid":"91","rating":"4","timestamp":"886483669"},{"itemid":"97","rating":"2","timestamp":"886483859"},{"itemid":"768","rating":"1","timestamp":"886483620"},{"itemid":"650","rating":"2","timestamp":"886480163"},{"itemid":"250","rating":"4","timestamp":"886480970"},{"itemid":"806","rating":"1","timestamp":"886483824"},{"itemid":"737","rating":"3","timestamp":"886484098"},{"itemid":"76","rating":"3","timestamp":"886484215"},{"itemid":"194","rating":"3","timestamp":"886480206"},{"itemid":"8","rating":"4","timestamp":"886480108"},{"itemid":"428","rating":"4","timestamp":"886482969"},{"itemid":"659","rating":"4","timestamp":"886480325"},{"itemid":"13","rating":"4","timestamp":"886480788"},{"itemid":"99","rating":"5","timestamp":"886483620"},{"itemid":"192","rating":"5","timestamp":"886484336"},{"itemid":"619","rating":"1","timestamp":"886481073"},{"itemid":"190","rating":"5","timestamp":"886483150"},{"itemid":"196","rating":"2","timestamp":"886484012"},{"itemid":"187","rating":"4","timestamp":"886483049"},{"itemid":"27","rating":"1","timestamp":"886483252"},{"itemid":"679","rating":"5","timestamp":"886483194"},{"itemid":"10","rating":"4","timestamp":"886481228"},{"itemid":"205","rating":"5","timestamp":"886480384"},{"itemid":"298","rating":"3","timestamp":"886480623"},{"itemid":"526","rating":"4","timestamp":"886483150"},{"itemid":"7","rating":"5","timestamp":"886479528"},{"itemid":"430","rating":"3","timestamp":"886482882"},{"itemid":"181","rating":"4","timestamp":"886479610"},{"itemid":"477","rating":"1","timestamp":"886480733"},{"itemid":"563","rating":"2","timestamp":"886481851"},{"itemid":"513","rating":"5","timestamp":"886483330"},{"itemid":"399","rating":"3","timestamp":"886482969"},{"itemid":"1187","rating":"4","timestamp":"886480623"},{"itemid":"28","rating":"5","timestamp":"886483939"},{"itemid":"567","rating":"2","timestamp":"886481737"},{"itemid":"1","rating":"4","timestamp":"886480681"},{"itemid":"12","rating":"5","timestamp":"886484336"},{"itemid":"232","rating":"2","timestamp":"886483289"},{"itemid":"581","rating":"4","timestamp":"886483394"},{"itemid":"727","rating":"5","timestamp":"886484098"},{"itemid":"514","rating":"3","timestamp":"886480515"},{"itemid":"692","rating":"1","timestamp":"886482928"},{"itemid":"773","rating":"4","timestamp":"886481800"},{"itemid":"183","rating":"4","timestamp":"886480206"},{"itemid":"566","rating":"3","timestamp":"886483194"},{"itemid":"1012","rating":"4","timestamp":"886481073"},{"itemid":"333","rating":"3","timestamp":"886479484"},{"itemid":"46","rating":"3","timestamp":"886484011"},{"itemid":"651","rating":"2","timestamp":"886479689"},{"itemid":"380","rating":"2","timestamp":"886484098"},{"itemid":"1143","rating":"5","timestamp":"886480623"},{"itemid":"744","rating":"3","timestamp":"886480818"},{"itemid":"189","rating":"5","timestamp":"886483619"},{"itemid":"294","rating":"2","timestamp":"886484413"},{"itemid":"114","rating":"5","timestamp":"886484336"},{"itemid":"357","rating":"5","timestamp":"886479690"},{"itemid":"233","rating":"3","timestamp":"886483151"},{"itemid":"319","rating":"1","timestamp":"886484384"},{"itemid":"293","rating":"4","timestamp":"886481002"},{"itemid":"470","rating":"3","timestamp":"886483970"},{"itemid":"972","rating":"2","timestamp":"886483859"},{"itemid":"769","rating":"1","timestamp":"886481851"},{"itemid":"593","rating":"3","timestamp":"886480483"},{"itemid":"102","rating":"3","timestamp":"886483669"},{"itemid":"265","rating":"4","timestamp":"886483049"},{"itemid":"20","rating":"4","timestamp":"886480789"},{"itemid":"582","rating":"3","timestamp":"886483497"},{"itemid":"23","rating":"2","timestamp":"886479528"},{"itemid":"79","rating":"4","timestamp":"886483049"},{"itemid":"732","rating":"1","timestamp":"886484215"},{"itemid":"684","rating":"3","timestamp":"886483099"},{"itemid":"325","rating":"2","timestamp":"886484460"},{"itemid":"515","rating":"5","timestamp":"886480755"},{"itemid":"193","rating":"5","timestamp":"886484065"},{"itemid":"258","rating":"4","timestamp":"886480818"},{"itemid":"295","rating":"3","timestamp":"886480818"},{"itemid":"231","rating":"3","timestamp":"886483194"},{"itemid":"62","rating":"2","timestamp":"886483252"},{"itemid":"642","rating":"4","timestamp":"886483395"},{"itemid":"11","rating":"3","timestamp":"886480325"},{"itemid":"1078","rating":"1","timestamp":"886483670"},{"itemid":"569","rating":"2","timestamp":"886481737"},{"itemid":"583","rating":"4","timestamp":"886483098"},{"itemid":"435","rating":"3","timestamp":"886480483"},{"itemid":"953","rating":"2","timestamp":"886484012"},{"itemid":"550","rating":"2","timestamp":"886483252"},{"itemid":"172","rating":"4","timestamp":"886480206"},{"itemid":"42","rating":"4","timestamp":"886480548"},{"itemid":"25","rating":"2","timestamp":"886481271"},{"itemid":"174","rating":"5","timestamp":"886480384"},{"itemid":"32","rating":"5","timestamp":"886479737"},{"itemid":"447","rating":"4","timestamp":"886481687"},{"itemid":"559","rating":"3","timestamp":"886481737"},{"itemid":"1019","rating":"4","timestamp":"886480288"},{"itemid":"198","rating":"4","timestamp":"886480352"},{"itemid":"1115","rating":"3","timestamp":"886479575"},{"itemid":"564","rating":"1","timestamp":"886481800"},{"itemid":"844","rating":"5","timestamp":"886480484"},{"itemid":"578","rating":"2","timestamp":"886483252"},{"itemid":"168","rating":"5","timestamp":"886479610"},{"itemid":"288","rating":"3","timestamp":"886484385"},{"itemid":"672","rating":"2","timestamp":"886481687"},{"itemid":"182","rating":"5","timestamp":"886483048"},{"itemid":"169","rating":"5","timestamp":"886484336"},{"itemid":"984","rating":"1","timestamp":"886484460"},{"itemid":"432","rating":"4","timestamp":"886480353"},{"itemid":"854","rating":"5","timestamp":"886481686"},{"itemid":"943","rating":"4","timestamp":"886483357"},{"itemid":"71","rating":"2","timestamp":"886483620"},{"itemid":"444","rating":"4","timestamp":"886481800"},{"itemid":"441","rating":"1","timestamp":"886481800"},{"itemid":"133","rating":"2","timestamp":"886480483"},{"itemid":"561","rating":"3","timestamp":"886481800"},{"itemid":"69","rating":"3","timestamp":"886480413"},{"itemid":"55","rating":"3","timestamp":"886479649"},{"itemid":"268","rating":"3","timestamp":"886479430"},{"itemid":"1537","rating":"4","timestamp":"886480681"},{"itemid":"1128","rating":"4","timestamp":"886481033"},{"itemid":"219","rating":"2","timestamp":"886481686"},{"itemid":"790","rating":"1","timestamp":"886482969"},{"itemid":"226","rating":"3","timestamp":"886483252"},{"itemid":"217","rating":"3","timestamp":"886481687"},{"itemid":"277","rating":"4","timestamp":"886481033"},{"itemid":"161","rating":"1","timestamp":"886483252"},{"itemid":"195","rating":"4","timestamp":"886479528"},{"itemid":"113","rating":"4","timestamp":"886479575"},{"itemid":"176","rating":"3","timestamp":"886480446"},{"itemid":"663","rating":"4","timestamp":"886482883"},{"itemid":"127","rating":"4","timestamp":"886479575"},{"itemid":"229","rating":"2","timestamp":"886483195"},{"itemid":"238","rating":"5","timestamp":"886482928"},{"itemid":"197","rating":"2","timestamp":"886483824"},{"itemid":"228","rating":"5","timestamp":"886484336"},{"itemid":"508","rating":"4","timestamp":"886479690"},{"itemid":"558","rating":"4","timestamp":"886480384"},{"itemid":"206","rating":"4","timestamp":"886483429"},{"itemid":"321","rating":"3","timestamp":"886484384"},{"itemid":"318","rating":"3","timestamp":"886479610"},{"itemid":"107","rating":"3","timestamp":"886481002"},{"itemid":"429","rating":"3","timestamp":"886484065"},{"itemid":"742","rating":"2","timestamp":"886481105"},{"itemid":"22","rating":"5","timestamp":"886483049"},{"itemid":"241","rating":"1","timestamp":"886483194"},{"itemid":"789","rating":"4","timestamp":"886482928"},{"itemid":"772","rating":"4","timestamp":"886483782"},{"itemid":"385","rating":"3","timestamp":"886483150"},{"itemid":"289","rating":"1","timestamp":"886484413"},{"itemid":"1011","rating":"3","timestamp":"886481033"},{"itemid":"286","rating":"2","timestamp":"886484385"},{"itemid":"521","rating":"3","timestamp":"886483906"},{"itemid":"191","rating":"4","timestamp":"886479610"},{"itemid":"179","rating":"5","timestamp":"886484336"},{"itemid":"551","rating":"2","timestamp":"886481800"},{"itemid":"530","rating":"4","timestamp":"886483099"},{"itemid":"153","rating":"4","timestamp":"886479649"},{"itemid":"665","rating":"2","timestamp":"886481851"},{"itemid":"408","rating":"4","timestamp":"886484492"},{"itemid":"414","rating":"4","timestamp":"886482969"},{"itemid":"520","rating":"4","timestamp":"886480446"},{"itemid":"58","rating":"4","timestamp":"886484065"},{"itemid":"381","rating":"4","timestamp":"886482969"},{"itemid":"82","rating":"4","timestamp":"886483098"},{"itemid":"448","rating":"3","timestamp":"886481686"},{"itemid":"697","rating":"1","timestamp":"886483906"},{"itemid":"693","rating":"5","timestamp":"886484336"},{"itemid":"488","rating":"3","timestamp":"886480163"},{"itemid":"1069","rating":"2","timestamp":"886480288"},{"itemid":"81","rating":"3","timestamp":"886483906"},{"itemid":"1118","rating":"3","timestamp":"886482695"},{"itemid":"436","rating":"4","timestamp":"886481737"},{"itemid":"431","rating":"3","timestamp":"886483150"},{"itemid":"136","rating":"3","timestamp":"886480288"},{"itemid":"202","rating":"3","timestamp":"886482695"},{"itemid":"52","rating":"5","timestamp":"886483497"},{"itemid":"273","rating":"4","timestamp":"886481151"},{"itemid":"223","rating":"5","timestamp":"886479771"},{"itemid":"1240","rating":"5","timestamp":"886483620"},{"itemid":"96","rating":"4","timestamp":"886480447"},{"itemid":"98","rating":"4","timestamp":"886480244"},{"itemid":"222","rating":"4","timestamp":"886481073"},{"itemid":"746","rating":"1","timestamp":"886479737"},{"itemid":"1134","rating":"1","timestamp":"886481183"},{"itemid":"151","rating":"3","timestamp":"886481228"},{"itemid":"1091","rating":"1","timestamp":"886483670"},{"itemid":"123","rating":"3","timestamp":"886480970"},{"itemid":"532","rating":"3","timestamp":"886480970"},{"itemid":"320","rating":"4","timestamp":"886480325"},{"itemid":"93","rating":"5","timestamp":"886480703"},{"itemid":"230","rating":"3","timestamp":"886483194"},{"itemid":"496","rating":"3","timestamp":"886480515"},{"itemid":"92","rating":"4","timestamp":"886483098"},{"itemid":"1018","rating":"3","timestamp":"886483526"},{"itemid":"625","rating":"2","timestamp":"886483669"},{"itemid":"434","rating":"5","timestamp":"886483970"},{"itemid":"410","rating":"3","timestamp":"886480789"},{"itemid":"678","rating":"3","timestamp":"886484460"},{"itemid":"580","rating":"5","timestamp":"886483565"},{"itemid":"919","rating":"5","timestamp":"886479575"},{"itemid":"33","rating":"3","timestamp":"886483098"},{"itemid":"186","rating":"2","timestamp":"886480515"},{"itemid":"211","rating":"4","timestamp":"886480108"},{"itemid":"89","rating":"5","timestamp":"886483048"},{"itemid":"475","rating":"3","timestamp":"886480657"},{"itemid":"248","rating":"4","timestamp":"886481151"},{"itemid":"29","rating":"1","timestamp":"886483252"},{"itemid":"109","rating":"4","timestamp":"886481073"},{"itemid":"239","rating":"1","timestamp":"886483970"},{"itemid":"175","rating":"5","timestamp":"886479771"},{"itemid":"100","rating":"5","timestamp":"886484336"},{"itemid":"718","rating":"4","timestamp":"886480206"},{"itemid":"588","rating":"3","timestamp":"886480163"},{"itemid":"367","rating":"3","timestamp":"886482883"},{"itemid":"324","rating":"4","timestamp":"886481002"},{"itemid":"53","rating":"4","timestamp":"886481737"},{"itemid":"95","rating":"2","timestamp":"886483620"},{"itemid":"676","rating":"1","timestamp":"886480733"},{"itemid":"568","rating":"2","timestamp":"886483099"},{"itemid":"641","rating":"5","timestamp":"886483824"},{"itemid":"847","rating":"3","timestamp":"886480325"},{"itemid":"1166","rating":"3","timestamp":"886483939"},{"itemid":"218","rating":"3","timestamp":"886481687"},{"itemid":"199","rating":"4","timestamp":"886483858"},{"itemid":"942","rating":"4","timestamp":"886483906"},{"itemid":"200","rating":"5","timestamp":"886481686"},{"itemid":"224","rating":"5","timestamp":"886480703"},{"itemid":"31","rating":"3","timestamp":"886483330"},{"itemid":"423","rating":"3","timestamp":"886484065"},{"itemid":"1097","rating":"3","timestamp":"886480657"},{"itemid":"201","rating":"5","timestamp":"886484631"},{"itemid":"208","rating":"3","timestamp":"886480484"},{"itemid":"144","rating":"3","timestamp":"886479649"},{"itemid":"501","rating":"4","timestamp":"886483620"},{"itemid":"674","rating":"2","timestamp":"886481686"},{"itemid":"845","rating":"4","timestamp":"886484336"},{"itemid":"317","rating":"4","timestamp":"886483906"},{"itemid":"152","rating":"1","timestamp":"886479690"},{"itemid":"227","rating":"4","timestamp":"886483195"},{"itemid":"418","rating":"3","timestamp":"886483669"},{"itemid":"210","rating":"4","timestamp":"886482928"},{"itemid":"2","rating":"4","timestamp":"886483195"},{"itemid":"458","rating":"1","timestamp":"886481183"},{"itemid":"203","rating":"4","timestamp":"886483330"},{"itemid":"1199","rating":"5","timestamp":"886480970"},{"itemid":"184","rating":"3","timestamp":"886481634"},{"itemid":"403","rating":"3","timestamp":"886483099"},{"itemid":"463","rating":"4","timestamp":"886483526"},{"itemid":"473","rating":"4","timestamp":"886481033"},{"itemid":"4","rating":"3","timestamp":"886482969"},{"itemid":"215","rating":"2","timestamp":"886483906"},{"itemid":"735","rating":"2","timestamp":"886484012"},{"itemid":"549","rating":"5","timestamp":"886484012"},{"itemid":"209","rating":"5","timestamp":"886480206"},{"itemid":"969","rating":"3","timestamp":"886480163"},{"itemid":"135","rating":"5","timestamp":"886480288"},{"itemid":"147","rating":"2","timestamp":"886481073"},{"itemid":"47","rating":"4","timestamp":"886480384"},{"itemid":"511","rating":"3","timestamp":"886483049"},{"itemid":"455","rating":"4","timestamp":"886481105"},{"itemid":"156","rating":"5","timestamp":"886484336"},{"itemid":"117","rating":"3","timestamp":"886480788"},{"itemid":"246","rating":"3","timestamp":"886480623"},{"itemid":"952","rating":"5","timestamp":"886484561"},{"itemid":"121","rating":"2","timestamp":"886481228"},{"itemid":"715","rating":"5","timestamp":"886484157"},{"itemid":"1129","rating":"4","timestamp":"886480623"},{"itemid":"446","rating":"2","timestamp":"886481800"},{"itemid":"774","rating":"3","timestamp":"886481737"},{"itemid":"474","rating":"5","timestamp":"886480163"},{"itemid":"528","rating":"4","timestamp":"886483906"},{"itemid":"856","rating":"5","timestamp":"886484124"},{"itemid":"129","rating":"5","timestamp":"886480583"},{"itemid":"68","rating":"4","timestamp":"886483099"},{"itemid":"101","rating":"4","timestamp":"886479528"},{"itemid":"1110","rating":"2","timestamp":"886483009"},{"itemid":"516","rating":"3","timestamp":"886482928"},{"itemid":"204","rating":"2","timestamp":"886479771"},{"itemid":"178","rating":"3","timestamp":"886483824"},{"itemid":"243","rating":"1","timestamp":"886484460"},{"itemid":"531","rating":"3","timestamp":"886479528"},{"itemid":"518","rating":"4","timestamp":"886483151"},{"itemid":"731","rating":"1","timestamp":"886482969"},{"itemid":"655","rating":"3","timestamp":"886480352"},{"itemid":"173","rating":"4","timestamp":"886480288"},{"itemid":"188","rating":"5","timestamp":"886483151"},{"itemid":"214","rating":"5","timestamp":"886483753"},{"itemid":"1198","rating":"3","timestamp":"886479575"}]}
{"userid":423,"gp":[{"itemid":"15","rating":"4","timestamp":"891395573"},{"itemid":"690","rating":"4","timestamp":"891394832"},{"itemid":"328","rating":"1","timestamp":"891394874"},{"itemid":"9","rating":"5","timestamp":"891395395"},{"itemid":"148","rating":"3","timestamp":"891395417"},{"itemid":"546","rating":"2","timestamp":"891395684"},{"itemid":"329","rating":"3","timestamp":"891394952"},{"itemid":"344","rating":"4","timestamp":"891394558"},{"itemid":"282","rating":"4","timestamp":"891395448"},{"itemid":"127","rating":"4","timestamp":"891395394"},{"itemid":"316","rating":"4","timestamp":"891394985"},{"itemid":"237","rating":"4","timestamp":"891395448"},{"itemid":"272","rating":"5","timestamp":"891394503"},{"itemid":"898","rating":"4","timestamp":"891394952"},{"itemid":"355","rating":"3","timestamp":"891395020"},{"itemid":"304","rating":"4","timestamp":"891394632"},{"itemid":"751","rating":"3","timestamp":"891394832"},{"itemid":"628","rating":"4","timestamp":"891395602"},{"itemid":"1238","rating":"3","timestamp":"891394874"},{"itemid":"125","rating":"2","timestamp":"891395547"},{"itemid":"299","rating":"3","timestamp":"891394788"},{"itemid":"245","rating":"4","timestamp":"891394952"},{"itemid":"748","rating":"3","timestamp":"891394985"},{"itemid":"591","rating":"5","timestamp":"891395547"},{"itemid":"750","rating":"5","timestamp":"891394704"},{"itemid":"887","rating":"5","timestamp":"891394673"},{"itemid":"10","rating":"4","timestamp":"891395734"},{"itemid":"508","rating":"4","timestamp":"891395394"},{"itemid":"310","rating":"3","timestamp":"891394558"},{"itemid":"300","rating":"3","timestamp":"891394874"},{"itemid":"333","rating":"3","timestamp":"891394747"},{"itemid":"327","rating":"2","timestamp":"891394673"},{"itemid":"347","rating":"3","timestamp":"891394632"},{"itemid":"696","rating":"3","timestamp":"891395759"},{"itemid":"471","rating":"3","timestamp":"891395626"},{"itemid":"924","rating":"4","timestamp":"891395602"},{"itemid":"823","rating":"3","timestamp":"891395759"},{"itemid":"307","rating":"3","timestamp":"891394673"},{"itemid":"879","rating":"3","timestamp":"891394558"},{"itemid":"620","rating":"4","timestamp":"891395711"},{"itemid":"339","rating":"2","timestamp":"891394788"},{"itemid":"315","rating":"4","timestamp":"891395141"},{"itemid":"1265","rating":"4","timestamp":"891394788"},{"itemid":"326","rating":"4","timestamp":"891394874"},{"itemid":"689","rating":"4","timestamp":"891395020"},{"itemid":"302","rating":"5","timestamp":"891394595"},{"itemid":"754","rating":"4","timestamp":"891394832"},{"itemid":"286","rating":"4","timestamp":"891394632"},{"itemid":"292","rating":"4","timestamp":"891394504"},{"itemid":"744","rating":"4","timestamp":"891395655"},{"itemid":"323","rating":"3","timestamp":"891395047"},{"itemid":"258","rating":"5","timestamp":"891394747"},{"itemid":"1134","rating":"4","timestamp":"891395684"},{"itemid":"269","rating":"3","timestamp":"891394558"},{"itemid":"348","rating":"3","timestamp":"891394910"},{"itemid":"1011","rating":"3","timestamp":"891395547"},{"itemid":"977","rating":"1","timestamp":"891395787"},{"itemid":"276","rating":"5","timestamp":"891395602"},{"itemid":"313","rating":"4","timestamp":"891394595"},{"itemid":"340","rating":"4","timestamp":"891394504"},{"itemid":"322","rating":"3","timestamp":"891395020"},{"itemid":"678","rating":"3","timestamp":"891395020"},{"itemid":"293","rating":"4","timestamp":"891395547"},{"itemid":"100","rating":"5","timestamp":"891395448"}]}
{"userid":695,"gp":[{"itemid":"882","rating":"4","timestamp":"888805836"},{"itemid":"903","rating":"4","timestamp":"888806082"},{"itemid":"748","rating":"1","timestamp":"888806270"},{"itemid":"333","rating":"2","timestamp":"888805952"},{"itemid":"343","rating":"4","timestamp":"888806120"},{"itemid":"340","rating":"4","timestamp":"888806082"},{"itemid":"300","rating":"1","timestamp":"888805767"},{"itemid":"995","rating":"4","timestamp":"888806150"},{"itemid":"346","rating":"5","timestamp":"888806011"},{"itemid":"305","rating":"3","timestamp":"888805797"},{"itemid":"268","rating":"5","timestamp":"888805864"},{"itemid":"264","rating":"1","timestamp":"888806222"},{"itemid":"328","rating":"3","timestamp":"888806056"},{"itemid":"312","rating":"3","timestamp":"888806193"},{"itemid":"302","rating":"4","timestamp":"888805836"},{"itemid":"307","rating":"4","timestamp":"888806120"},{"itemid":"319","rating":"5","timestamp":"888806056"},{"itemid":"1024","rating":"5","timestamp":"888805913"},{"itemid":"895","rating":"1","timestamp":"888805864"},{"itemid":"323","rating":"2","timestamp":"888806292"},{"itemid":"678","rating":"4","timestamp":"888806292"},{"itemid":"358","rating":"5","timestamp":"888806270"},{"itemid":"301","rating":"3","timestamp":"888806120"},{"itemid":"260","rating":"4","timestamp":"888806150"},{"itemid":"311","rating":"4","timestamp":"888805767"},{"itemid":"991","rating":"5","timestamp":"888806011"},{"itemid":"354","rating":"4","timestamp":"888806056"},{"itemid":"338","rating":"2","timestamp":"888806270"},{"itemid":"313","rating":"2","timestamp":"888805836"},{"itemid":"270","rating":"4","timestamp":"888805952"},{"itemid":"288","rating":"4","timestamp":"888806120"},{"itemid":"242","rating":"5","timestamp":"888805837"},{"itemid":"682","rating":"1","timestamp":"888805952"},{"itemid":"324","rating":"2","timestamp":"888805981"},{"itemid":"289","rating":"2","timestamp":"888806150"},{"itemid":"887","rating":"3","timestamp":"888805797"},{"itemid":"286","rating":"3","timestamp":"888805913"},{"itemid":"989","rating":"3","timestamp":"888806056"}]}
{"userid":746,"gp":[{"itemid":"117","rating":"4","timestamp":"885075304"},{"itemid":"184","rating":"4","timestamp":"885075267"},{"itemid":"38","rating":"2","timestamp":"885075476"},{"itemid":"181","rating":"5","timestamp":"885075166"},{"itemid":"578","rating":"4","timestamp":"885075399"},{"itemid":"1","rating":"4","timestamp":"885075714"},{"itemid":"222","rating":"3","timestamp":"885075267"},{"itemid":"89","rating":"4","timestamp":"885075243"},{"itemid":"172","rating":"5","timestamp":"885075165"},{"itemid":"183","rating":"4","timestamp":"885075165"},{"itemid":"403","rating":"4","timestamp":"885075337"},{"itemid":"568","rating":"4","timestamp":"885075211"},{"itemid":"82","rating":"4","timestamp":"885075337"},{"itemid":"423","rating":"3","timestamp":"885075612"},{"itemid":"132","rating":"4","timestamp":"885075756"},{"itemid":"597","rating":"4","timestamp":"885075304"},{"itemid":"233","rating":"4","timestamp":"885075399"},{"itemid":"168","rating":"3","timestamp":"885075790"},{"itemid":"128","rating":"3","timestamp":"885075211"},{"itemid":"231","rating":"2","timestamp":"885075476"},{"itemid":"226","rating":"4","timestamp":"885075434"},{"itemid":"202","rating":"5","timestamp":"885075518"},{"itemid":"8","rating":"4","timestamp":"885075539"},{"itemid":"506","rating":"3","timestamp":"885075824"},{"itemid":"265","rating":"4","timestamp":"885075399"},{"itemid":"186","rating":"4","timestamp":"885075497"},{"itemid":"135","rating":"1","timestamp":"885075655"},{"itemid":"83","rating":"4","timestamp":"885075497"},{"itemid":"546","rating":"3","timestamp":"885075434"},{"itemid":"56","rating":"3","timestamp":"885075211"},{"itemid":"431","rating":"5","timestamp":"885075304"},{"itemid":"230","rating":"1","timestamp":"885075337"},{"itemid":"449","rating":"1","timestamp":"885075476"},{"itemid":"685","rating":"3","timestamp":"885075304"},{"itemid":"121","rating":"3","timestamp":"885075337"},{"itemid":"455","rating":"4","timestamp":"885075304"},{"itemid":"405","rating":"2","timestamp":"885075476"},{"itemid":"720","rating":"3","timestamp":"885075399"},{"itemid":"208","rating":"4","timestamp":"885075569"},{"itemid":"96","rating":"4","timestamp":"885075267"},{"itemid":"196","rating":"4","timestamp":"885075612"},{"itemid":"566","rating":"4","timestamp":"885075367"},{"itemid":"232","rating":"3","timestamp":"885075304"},{"itemid":"157","rating":"4","timestamp":"885075590"},{"itemid":"399","rating":"3","timestamp":"885075211"},{"itemid":"79","rating":"5","timestamp":"885075165"},{"itemid":"24","rating":"4","timestamp":"885075434"},{"itemid":"684","rating":"4","timestamp":"885075337"},{"itemid":"385","rating":"5","timestamp":"885075367"},{"itemid":"22","rating":"4","timestamp":"885075211"},{"itemid":"174","rating":"5","timestamp":"885075243"},{"itemid":"68","rating":"4","timestamp":"885075337"},{"itemid":"210","rating":"5","timestamp":"885075211"},{"itemid":"228","rating":"4","timestamp":"885075243"},{"itemid":"550","rating":"4","timestamp":"885075367"},{"itemid":"523","rating":"3","timestamp":"885075497"},{"itemid":"50","rating":"5","timestamp":"885075165"},{"itemid":"144","rating":"5","timestamp":"885075211"},{"itemid":"127","rating":"2","timestamp":"885075243"},{"itemid":"62","rating":"3","timestamp":"885075434"},{"itemid":"281","rating":"3","timestamp":"885075434"},{"itemid":"204","rating":"5","timestamp":"885075539"},{"itemid":"161","rating":"3","timestamp":"885075304"},{"itemid":"64","rating":"4","timestamp":"885075790"},{"itemid":"2","rating":"3","timestamp":"885075304"},{"itemid":"229","rating":"2","timestamp":"885075399"},{"itemid":"176","rating":"5","timestamp":"885075243"}]}
